hyperfine/__init__.py
hyperfine/_version.py
hyperfine/demagnetization.py
hyperfine/distributions.py
hyperfine/minuit.py
hyperfine/utilities.py
hyperfine/bnmr/__init__.py
hyperfine/bnmr/lineshape.py
hyperfine/bnmr/meissner.py
hyperfine/bnmr/nlme.py
hyperfine/bnmr/susceptibility.py
hyperfine/bnmr/two_site.py
hyperfine/implantation/__init__.py
hyperfine/implantation/dpass.py
hyperfine/implantation/electronic_stopping.py
hyperfine/implantation/srim.py
hyperfine/musr/__init__.py
hyperfine/musr/_meissner.py
hyperfine/musr/meissner.py
hyperfine/superconductivity/__init__.py
hyperfine/superconductivity/_muhlschlegel.py
hyperfine/superconductivity/bcs.py
hyperfine/superconductivity/ccf.py
hyperfine/superconductivity/interpolation.py
hyperfine/superconductivity/intertype.py
hyperfine/superconductivity/london.py
hyperfine/superconductivity/pippard.py
hyperfine-0.1.3.dist-info/METADATA
hyperfine-0.1.3.dist-info/WHEEL
hyperfine-0.1.3.dist-info/licenses/LICENSE
hyperfine-0.1.3.dist-info/RECORD
