Metadata-Version: 2.3
Name: hyperfine
Version: 0.1.3
Project-URL: Homepage, https://github.com/rmlmcfadden/hyperfine
Project-URL: Documentation, https://hyperfine.readthedocs.io/
Project-URL: Repository, https://github.com/rmlmcfadden/hyperfine.git
Project-URL: Issues, https://github.com/rmlmcfadden/hyperfine/issues
Author-email: "Ryan M. L. McFadden" <rmlm@triumf.ca>
License: MIT
Keywords: DPASS,SRIM,condensed matter,ion-implantation,materials science,superconductivity,β-NMR,μSR
Classifier: Development Status :: 2 - Pre-Alpha
Classifier: Intended Audience :: Science/Research
Classifier: License :: OSI Approved :: MIT License
Classifier: Natural Language :: English
Classifier: Operating System :: POSIX :: Linux
Classifier: Programming Language :: Python :: 3
Classifier: Programming Language :: Python :: 3.8
Classifier: Programming Language :: Python :: 3.9
Classifier: Programming Language :: Python :: 3.10
Classifier: Programming Language :: Python :: 3.11
Classifier: Programming Language :: Python :: 3.12
Classifier: Topic :: Scientific/Engineering
Classifier: Topic :: Scientific/Engineering :: Chemistry
Classifier: Topic :: Scientific/Engineering :: Physics
Requires-Python: >=3.8
Requires-Dist: iminuit>=2.24.0
Requires-Dist: jax>=0.4.30
Requires-Dist: joblib>=1.2.0
Requires-Dist: numpy>=1.23.0
Requires-Dist: pandas>=1.5.0
Requires-Dist: scipy>=1.10.0
